sparksnake/__init__.py
sparksnake/glue.py
sparksnake/manager.py
sparksnake/tester/__init__.py
sparksnake/tester/dataframes.py
sparksnake/utils/__init__.py
sparksnake/utils/log.py
tests/__init__.py
tests/conftest.py
tests/test_glue_module.py
tests/test_manager_module.py
tests/test_tester_dataframes.py
tests/test_utils_log.py
tests/helpers/__init__.py
tests/helpers/user_inputs.py
sparksnake-0.2.2.dist-info/LICENSE
sparksnake-0.2.2.dist-info/METADATA
sparksnake-0.2.2.dist-info/WHEEL
sparksnake-0.2.2.dist-info/top_level.txt
sparksnake-0.2.2.dist-info/RECORD
